oftp_news/__init__.py
oftp_news/main.py
oftp_news-0.1.2.dist-info/METADATA
oftp_news-0.1.2.dist-info/WHEEL
oftp_news-0.1.2.dist-info/RECORD
